AndroidTraceTool
